mseep_hayhooks-1.0.0.dist-info/licenses/LICENSE
tests/__init__.py
tests/conftest.py
tests/test_cli.py
tests/test_convert_component_output.py
tests/test_cors.py
tests/test_deploy_at_startup.py
tests/test_deploy_utils.py
tests/test_handle_callable_type.py
tests/test_handle_unsupported_types.py
tests/test_it_deploy.py
tests/test_it_deploy_files.py
tests/test_it_draw.py
tests/test_it_handling_deploy_exceptions.py
tests/test_it_mcp_server.py
tests/test_it_openai.py
tests/test_it_pipeline_utils.py
tests/test_it_status.py
tests/test_mcp.py
tests/test_open_webui.py
tests/test_pipeline_run.py
tests/test_registry.py
tests/test_settings.py
tests/test_undeploy.py
tests/test_utils.py
mseep_hayhooks-1.0.0.dist-info/METADATA
mseep_hayhooks-1.0.0.dist-info/WHEEL
mseep_hayhooks-1.0.0.dist-info/top_level.txt
mseep_hayhooks-1.0.0.dist-info/RECORD
