Metadata-Version: 2.4
Name: mseep-hayhooks
Version: 1.0.0
Summary: Grab and deploy Haystack pipelines
Home-page: https://github.com/mseep
Author: mseep
Author-email: support@skydeck.ai
Maintainer: mseep
Maintainer-email: support@skydeck.ai
Keywords: mseep
Classifier: Programming Language :: Python :: 3
Classifier: License :: OSI Approved :: MIT License
Classifier: Operating System :: OS Independent
Requires-Python: >=3.6
License-File: LICENSE
Requires-Dist: haystack-ai>=2.11.0
Requires-Dist: fastapi[standard]
Requires-Dist: typer
Requires-Dist: uvicorn
Requires-Dist: rich
Requires-Dist: requests
Requires-Dist: python-multipart
Requires-Dist: loguru
Requires-Dist: pydantic-settings
Requires-Dist: python-dotenv
Requires-Dist: docstring-parser
Dynamic: author
Dynamic: author-email
Dynamic: classifier
Dynamic: description
Dynamic: description-content-type
Dynamic: home-page
Dynamic: keywords
Dynamic: license-file
Dynamic: maintainer
Dynamic: maintainer-email
Dynamic: requires-dist
Dynamic: requires-python
Dynamic: summary
